{
  "search_results": [
    {
      "position": 1,
      "title": "Remedy Ginger Beer - Sugar Free, USDA Organic & Low Calorie Mixer Drink - Non Alcoholic & Made With Real Ginger - 8.5 Fl Oz Can, 12-Pack",
      "asin": "B09D8VKGPN",
      "link": "https://www.amazon.com/Remedy-Ginger-Beer-Organic-Alcoholic/dp/B09D8VKGPN/ref=sr_1_1_mod_primary_new?keywords=beer+alcoholic+drinks&qid=1667472794&qu=eyJxc2MiOiIyLjYxIiwicXNhIjoiMC4wMCIsInFzcCI6IjAuMDAifQ%3D%3D&sbo=RZvfv%2F%2FHxDF%2BO5021pAnSA%3D%3D&sr=8-1",
      "categories": [
        {
          "name": "All Departments",
          "id": "aps"
        }
      ],
      "image": "https://m.media-amazon.com/images/I/810-gdh4KWL._AC_UL320_.jpg",
      "is_prime": true,
      "rating": 3.7,
      "ratings_total": 359,
      "prices": [
        {
          "symbol": "$",
          "value": 24.99,
          "currency": "USD",
          "raw": "$24.99",
          "name": "$24.99"
        },
        {
          "symbol": "$",
          "value": 22.49,
          "currency": "USD",
          "raw": "$22.49",
          "name": "$22.49"
        }
      ],
      "price": {
        "symbol": "$",
        "value": 24.99,
        "currency": "USD",
        "raw": "$24.99",
        "name": "$24.99"
      }
    },
    {
      "position": 2,
      "title": "Athletic Brewing Company Craft Non Alcoholic Beer - 6-Pack of All Out, Upside Dawn, Run Wild IPA, and Cerveza Atletica - Low-Calorie, Award Winning - All Natural Ingredients For A Great Tasting Drink - 12 Fl Oz Cans",
      "asin": "B08KTLN85W",
      "link": "https://www.amazon.com/Athletic-Brewing-Company-Craft-Low-Calorie/dp/B08KTLN85W/ref=sr_1_2?keywords=beer+alcoholic+drinks&qid=1667472794&qu=eyJxc2MiOiIyLjYxIiwicXNhIjoiMC4wMCIsInFzcCI6IjAuMDAifQ%3D%3D&sr=8-2",
      "categories": [
        {
          "name": "All Departments",
          "id": "aps"
        }
      ],
      "image": "https://m.media-amazon.com/images/I/71-Tb7LhOQL._AC_UL320_.jpg",
      "rating": 4.7,
      "ratings_total": 1247
    },
    {
      "position": 3,
      "title": "Athletic Brewing Company Craft Non-Alcoholic Beer - 24 Pack x 12 Fl Oz Cans - Run Wild IPA - Low-Calorie, Award Winning - The Ultimate Sessionable IPA Subtle Yet Complex Malt Profile",
      "asin": "B08J4KV2XV",
      "link": "https://www.amazon.com/Athletic-Brewing-Company-Craft-Low-Calorie/dp/B08J4KV2XV/ref=sr_1_3?keywords=beer+alcoholic+drinks&qid=1667472794&qu=eyJxc2MiOiIyLjYxIiwicXNhIjoiMC4wMCIsInFzcCI6IjAuMDAifQ%3D%3D&sr=8-3",
      "categories": [
        {
          "name": "All Departments",
          "id": "aps"
        }
      ],
      "image": "https://m.media-amazon.com/images/I/61m6PRemL7L._AC_UL320_.jpg",
      "rating": 4.8,
      "ratings_total": 75
    },
    {
      "position": 4,
      "title": "Guinness 0.0% ALC,DRAUGHT Non-Alcoholic N/A Stout Beer, 14.9 Fl Oz (Pack of 6)",
      "asin": "B09XP61DRB",
      "link": "https://www.amazon.com/Guinness-0-0-DRAUGHT-Non-Alcoholic-Stout/dp/B09XP61DRB/ref=sr_1_4?keywords=beer+alcoholic+drinks&qid=1667472794&qu=eyJxc2MiOiIyLjYxIiwicXNhIjoiMC4wMCIsInFzcCI6IjAuMDAifQ%3D%3D&sr=8-4",
      "categories": [
        {
          "name": "All Departments",
          "id": "aps"
        }
      ],
      "image": "https://m.media-amazon.com/images/I/71xWwpcrztL._AC_UL320_.jpg",
      "rating": 2.7,
      "ratings_total": 10,
      "prices": [
        {
          "symbol": "$",
          "value": 23.99,
          "currency": "USD",
          "raw": "$23.99",
          "name": "$23.99",
          "is_primary": true
        },
        {
          "symbol": "$",
          "value": 28.95,
          "currency": "USD",
          "raw": "$28.95",
          "name": "$23.99",
          "is_rrp": true
        }
      ],
      "price": {
        "symbol": "$",
        "value": 23.99,
        "currency": "USD",
        "raw": "$23.99",
        "name": "$23.99",
        "is_primary": true
      }
    },
    {
      "position": 5,
      "title": "WELLBEING BREWING CO. 6 Pack Cans Heavenly Body Golden Wheat Non-Alcoholic Craft Beer - 68 Calories - Zero Grams of Sugar - Vegan - non-GMO - High in Anti-Oxidants / Anti-Inflammatories - 12 Fl. oz",
      "asin": "B07FYV87C5",
      "link": "https://www.amazon.com/WELLBEING-BREWING-CO-Heavenly-Non-Alcoholic/dp/B07FYV87C5/ref=sr_1_5?keywords=beer+alcoholic+drinks&qid=1667472794&qu=eyJxc2MiOiIyLjYxIiwicXNhIjoiMC4wMCIsInFzcCI6IjAuMDAifQ%3D%3D&sr=8-5",
      "categories": [
        {
          "name": "All Departments",
          "id": "aps"
        }
      ],
      "image": "https://m.media-amazon.com/images/I/918gXcE5GPL._AC_UL320_.jpg",
      "rating": 4.2,
      "ratings_total": 218,
      "is_small_business": true,
      "prices": [
        {
          "symbol": "$",
          "value": 11.99,
          "currency": "USD",
          "raw": "$11.99",
          "name": "$11.99",
          "asin": "B07FYV87C5",
          "link": "https://www.amazon.com/WELLBEING-BREWING-CO-Heavenly-Non-Alcoholic/dp/B07FYV87C5/ref=sr_1_5?keywords=beer+alcoholic+drinks&qid=1667472794&qu=eyJxc2MiOiIyLjYxIiwicXNhIjoiMC4wMCIsInFzcCI6IjAuMDAifQ%3D%3D&sr=8-5"
        }
      ],
      "price": {
        "symbol": "$",
        "value": 11.99,
        "currency": "USD",
        "raw": "$11.99",
        "name": "$11.99",
        "asin": "B07FYV87C5",
        "link": "https://www.amazon.com/WELLBEING-BREWING-CO-Heavenly-Non-Alcoholic/dp/B07FYV87C5/ref=sr_1_5?keywords=beer+alcoholic+drinks&qid=1667472794&qu=eyJxc2MiOiIyLjYxIiwicXNhIjoiMC4wMCIsInFzcCI6IjAuMDAifQ%3D%3D&sr=8-5"
      }
    },
    {
      "position": 6,
      "title": "[Pack of 8] Worldwide Mix NA Non Alcoholic Beer Beverage Drinks In Cans, Variety Combo Pack, Great Gift Set! - Guinness, Heineken, Estrella Galicia, Ninja Larger, Suntory & More! (Domestic + International)",
      "asin": "B0B9DHFHQZ",
      "link": "https://www.amazon.com/Worldwide-Alcoholic-Beverage-Drinks-Variety/dp/B0B9DHFHQZ/ref=sr_1_6?keywords=beer+alcoholic+drinks&qid=1667472794&qu=eyJxc2MiOiIyLjYxIiwicXNhIjoiMC4wMCIsInFzcCI6IjAuMDAifQ%3D%3D&sr=8-6",
      "categories": [
        {
          "name": "All Departments",
          "id": "aps"
        }
      ],
      "image": "https://m.media-amazon.com/images/I/81q4rRANa+L._AC_UL320_.jpg",
      "is_prime": true,
      "rating": 2.5,
      "ratings_total": 2,
      "prices": [
        {
          "symbol": "$",
          "value": 36.95,
          "currency": "USD",
          "raw": "$36.95",
          "name": "$36.95",
          "asin": "B0B9DHFHQZ",
          "link": "https://www.amazon.com/Worldwide-Alcoholic-Beverage-Drinks-Variety/dp/B0B9DHFHQZ/ref=sr_1_6?keywords=beer+alcoholic+drinks&qid=1667472794&qu=eyJxc2MiOiIyLjYxIiwicXNhIjoiMC4wMCIsInFzcCI6IjAuMDAifQ%3D%3D&sr=8-6"
        }
      ],
      "price": {
        "symbol": "$",
        "value": 36.95,
        "currency": "USD",
        "raw": "$36.95",
        "name": "$36.95",
        "asin": "B0B9DHFHQZ",
        "link": "https://www.amazon.com/Worldwide-Alcoholic-Beverage-Drinks-Variety/dp/B0B9DHFHQZ/ref=sr_1_6?keywords=beer+alcoholic+drinks&qid=1667472794&qu=eyJxc2MiOiIyLjYxIiwicXNhIjoiMC4wMCIsInFzcCI6IjAuMDAifQ%3D%3D&sr=8-6"
      }
    },
    {
      "position": 7,
      "title": "Dream Light by Kin Euphorics, Non Alcoholic Spirits, Nootropic, Botanic, Adaptogen Drink, Earthy Oak, Smoky Clove and Spicy Cinnamon, Soothe The Spirit and Quiet The Mind, 16.9 Fl Oz",
      "asin": "B084YPNP2Y",
      "link": "https://www.amazon.com/Kin-Euphorics-Adaptogenic-Nootropic-Supplement/dp/B084YPNP2Y/ref=sr_1_7?keywords=beer+alcoholic+drinks&qid=1667472794&qu=eyJxc2MiOiIyLjYxIiwicXNhIjoiMC4wMCIsInFzcCI6IjAuMDAifQ%3D%3D&sr=8-7",
      "availability": {
        "raw": "Only 2 left in stock - order soon."
      },
      "categories": [
        {
          "name": "All Departments",
          "id": "aps"
        }
      ],
      "image": "https://m.media-amazon.com/images/I/614xIBKUJdL._AC_UL320_.jpg",
      "is_prime": true,
      "rating": 3.6,
      "ratings_total": 622,
      "is_small_business": true,
      "prices": [
        {
          "symbol": "$",
          "value": 39,
          "currency": "USD",
          "raw": "$39.00",
          "name": "$39.00",
          "asin": "B084YPNP2Y",
          "link": "https://www.amazon.com/Kin-Euphorics-Adaptogenic-Nootropic-Supplement/dp/B084YPNP2Y/ref=sr_1_7?keywords=beer+alcoholic+drinks&qid=1667472794&qu=eyJxc2MiOiIyLjYxIiwicXNhIjoiMC4wMCIsInFzcCI6IjAuMDAifQ%3D%3D&sr=8-7"
        }
      ],
      "price": {
        "symbol": "$",
        "value": 39,
        "currency": "USD",
        "raw": "$39.00",
        "name": "$39.00",
        "asin": "B084YPNP2Y",
        "link": "https://www.amazon.com/Kin-Euphorics-Adaptogenic-Nootropic-Supplement/dp/B084YPNP2Y/ref=sr_1_7?keywords=beer+alcoholic+drinks&qid=1667472794&qu=eyJxc2MiOiIyLjYxIiwicXNhIjoiMC4wMCIsInFzcCI6IjAuMDAifQ%3D%3D&sr=8-7"
      }
    },
    {
      "position": 8,
      "title": "Lightwave by Kin Euphorics, Non Alcoholic Spirits, Ready to Drink, Nootropic, Botanic, Adaptogen Drink, Lavender-Vanilla, Ginger, and Birch, Calm the Mind and Mellow the Mood, 8 Fl Oz (4pk)",
      "asin": "B09D1NFPYQ",
      "link": "https://www.amazon.com/Lightwave-Kin-Euphorics-Alcoholic-Lavender-Vanilla/dp/B09D1NFPYQ/ref=sr_1_8?keywords=beer+alcoholic+drinks&qid=1667472794&qu=eyJxc2MiOiIyLjYxIiwicXNhIjoiMC4wMCIsInFzcCI6IjAuMDAifQ%3D%3D&sr=8-8",
      "categories": [
        {
          "name": "All Departments",
          "id": "aps"
        }
      ],
      "image": "https://m.media-amazon.com/images/I/81QMI7LVs1L._AC_UL320_.jpg",
      "is_prime": true,
      "rating": 3.7,
      "ratings_total": 567,
      "is_small_business": true,
      "prices": [
        {
          "symbol": "$",
          "value": 22.49,
          "currency": "USD",
          "raw": "$22.49",
          "name": "$22.49",
          "asin": "B09D1NFPYQ",
          "link": "https://www.amazon.com/Lightwave-Kin-Euphorics-Alcoholic-Lavender-Vanilla/dp/B09D1NFPYQ/ref=sr_1_8?keywords=beer+alcoholic+drinks&qid=1667472794&qu=eyJxc2MiOiIyLjYxIiwicXNhIjoiMC4wMCIsInFzcCI6IjAuMDAifQ%3D%3D&sr=8-8"
        }
      ],
      "price": {
        "symbol": "$",
        "value": 22.49,
        "currency": "USD",
        "raw": "$22.49",
        "name": "$22.49",
        "asin": "B09D1NFPYQ",
        "link": "https://www.amazon.com/Lightwave-Kin-Euphorics-Alcoholic-Lavender-Vanilla/dp/B09D1NFPYQ/ref=sr_1_8?keywords=beer+alcoholic+drinks&qid=1667472794&qu=eyJxc2MiOiIyLjYxIiwicXNhIjoiMC4wMCIsInFzcCI6IjAuMDAifQ%3D%3D&sr=8-8"
      }
    },
    {
      "position": 9,
      "title": "Flying Cauldron Butterscotch Beer Non Alcoholic Butterscotch Cream Soda (2 Pack) with 2 Gosutoys Stickers",
      "asin": "B09VJJQCBV",
      "link": "https://www.amazon.com/Cauldron-Butterscotch-Alcoholic-Gosutoys-Stickers/dp/B09VJJQCBV/ref=sr_1_9?keywords=beer+alcoholic+drinks&qid=1667472794&qu=eyJxc2MiOiIyLjYxIiwicXNhIjoiMC4wMCIsInFzcCI6IjAuMDAifQ%3D%3D&sr=8-9",
      "availability": {
        "raw": "Only 7 left in stock - order soon."
      },
      "categories": [
        {
          "name": "All Departments",
          "id": "aps"
        }
      ],
      "image": "https://m.media-amazon.com/images/I/71ZrJDIXLAL._AC_UL320_.jpg",
      "is_prime": true,
      "rating": 3.7,
      "ratings_total": 7,
      "prices": [
        {
          "symbol": "$",
          "value": 12.99,
          "currency": "USD",
          "raw": "$12.99",
          "name": "$12.99",
          "asin": "B09VJJQCBV",
          "link": "https://www.amazon.com/Cauldron-Butterscotch-Alcoholic-Gosutoys-Stickers/dp/B09VJJQCBV/ref=sr_1_9?keywords=beer+alcoholic+drinks&qid=1667472794&qu=eyJxc2MiOiIyLjYxIiwicXNhIjoiMC4wMCIsInFzcCI6IjAuMDAifQ%3D%3D&sr=8-9"
        }
      ],
      "price": {
        "symbol": "$",
        "value": 12.99,
        "currency": "USD",
        "raw": "$12.99",
        "name": "$12.99",
        "asin": "B09VJJQCBV",
        "link": "https://www.amazon.com/Cauldron-Butterscotch-Alcoholic-Gosutoys-Stickers/dp/B09VJJQCBV/ref=sr_1_9?keywords=beer+alcoholic+drinks&qid=1667472794&qu=eyJxc2MiOiIyLjYxIiwicXNhIjoiMC4wMCIsInFzcCI6IjAuMDAifQ%3D%3D&sr=8-9"
      }
    },
    {
      "position": 10,
      "title": "Pabst Blue Ribbon N/A NON-ALCOHOLIC BEER, Made in USA, - 12 Fl Oz (24 Pack)",
      "asin": "B07RLZ1H32",
      "link": "https://www.amazon.com/Pabst-Blue-Ribbon-NON-ALCOHOLIC-BEER/dp/B07RLZ1H32/ref=sr_1_10?keywords=beer+alcoholic+drinks&qid=1667472794&qu=eyJxc2MiOiIyLjYxIiwicXNhIjoiMC4wMCIsInFzcCI6IjAuMDAifQ%3D%3D&sr=8-10",
      "categories": [
        {
          "name": "All Departments",
          "id": "aps"
        }
      ],
      "image": "https://m.media-amazon.com/images/I/51NhxHofzOL._AC_UL320_.jpg",
      "rating": 3.5,
      "ratings_total": 3,
      "prices": [
        {
          "symbol": "$",
          "value": 58.99,
          "currency": "USD",
          "raw": "$58.99",
          "name": "$58.99",
          "asin": "B07RLZ1H32",
          "link": "https://www.amazon.com/Pabst-Blue-Ribbon-NON-ALCOHOLIC-BEER/dp/B07RLZ1H32/ref=sr_1_10?keywords=beer+alcoholic+drinks&qid=1667472794&qu=eyJxc2MiOiIyLjYxIiwicXNhIjoiMC4wMCIsInFzcCI6IjAuMDAifQ%3D%3D&sr=8-10"
        }
      ],
      "price": {
        "symbol": "$",
        "value": 58.99,
        "currency": "USD",
        "raw": "$58.99",
        "name": "$58.99",
        "asin": "B07RLZ1H32",
        "link": "https://www.amazon.com/Pabst-Blue-Ribbon-NON-ALCOHOLIC-BEER/dp/B07RLZ1H32/ref=sr_1_10?keywords=beer+alcoholic+drinks&qid=1667472794&qu=eyJxc2MiOiIyLjYxIiwicXNhIjoiMC4wMCIsInFzcCI6IjAuMDAifQ%3D%3D&sr=8-10"
      }
    },
    {
      "position": 11,
      "title": "St Pauli German Non-alcoholic Beer 6 Bottlles",
      "asin": "B00TGF8534",
      "link": "https://www.amazon.com/St-Pauli-German-Non-alcoholic-Bottlles/dp/B00TGF8534/ref=sr_1_11?keywords=beer+alcoholic+drinks&qid=1667472794&qu=eyJxc2MiOiIyLjYxIiwicXNhIjoiMC4wMCIsInFzcCI6IjAuMDAifQ%3D%3D&sr=8-11",
      "availability": {
        "raw": "Only 4 left in stock - order soon."
      },
      "categories": [
        {
          "name": "All Departments",
          "id": "aps"
        }
      ],
      "image": "https://m.media-amazon.com/images/I/51EgPsbnRRL._AC_UL320_.jpg",
      "rating": 4,
      "ratings_total": 32,
      "prices": [
        {
          "symbol": "$",
          "value": 28.99,
          "currency": "USD",
          "raw": "$28.99",
          "name": "$28.99",
          "asin": "B00TGF8534",
          "link": "https://www.amazon.com/St-Pauli-German-Non-alcoholic-Bottlles/dp/B00TGF8534/ref=sr_1_11?keywords=beer+alcoholic+drinks&qid=1667472794&qu=eyJxc2MiOiIyLjYxIiwicXNhIjoiMC4wMCIsInFzcCI6IjAuMDAifQ%3D%3D&sr=8-11"
        }
      ],
      "price": {
        "symbol": "$",
        "value": 28.99,
        "currency": "USD",
        "raw": "$28.99",
        "name": "$28.99",
        "asin": "B00TGF8534",
        "link": "https://www.amazon.com/St-Pauli-German-Non-alcoholic-Bottlles/dp/B00TGF8534/ref=sr_1_11?keywords=beer+alcoholic+drinks&qid=1667472794&qu=eyJxc2MiOiIyLjYxIiwicXNhIjoiMC4wMCIsInFzcCI6IjAuMDAifQ%3D%3D&sr=8-11"
      }
    },
    {
      "position": 12,
      "title": "BrewDog 12-Pack of Nanny State | Non-Alcoholic, Hoppy Ale | 20 Calories, 2.3g Carbs Per Serving | 12oz Cans",
      "asin": "B08FSJQHP7",
      "link": "https://www.amazon.com/BrewDog-Nanny-Non-Alcoholic-Calories-Serving/dp/B08FSJQHP7/ref=sr_1_12?keywords=beer+alcoholic+drinks&qid=1667472794&qu=eyJxc2MiOiIyLjYxIiwicXNhIjoiMC4wMCIsInFzcCI6IjAuMDAifQ%3D%3D&sr=8-12",
      "availability": {
        "raw": "Only 14 left in stock - order soon."
      },
      "categories": [
        {
          "name": "All Departments",
          "id": "aps"
        }
      ],
      "image": "https://m.media-amazon.com/images/I/81KzopeuEpL._AC_UL320_.jpg",
      "rating": 4,
      "ratings_total": 65,
      "prices": [
        {
          "symbol": "$",
          "value": 29.99,
          "currency": "USD",
          "raw": "$29.99",
          "name": "$29.99",
          "asin": "B08FSJQHP7",
          "link": "https://www.amazon.com/BrewDog-Nanny-Non-Alcoholic-Calories-Serving/dp/B08FSJQHP7/ref=sr_1_12?keywords=beer+alcoholic+drinks&qid=1667472794&qu=eyJxc2MiOiIyLjYxIiwicXNhIjoiMC4wMCIsInFzcCI6IjAuMDAifQ%3D%3D&sr=8-12"
        }
      ],
      "price": {
        "symbol": "$",
        "value": 29.99,
        "currency": "USD",
        "raw": "$29.99",
        "name": "$29.99",
        "asin": "B08FSJQHP7",
        "link": "https://www.amazon.com/BrewDog-Nanny-Non-Alcoholic-Calories-Serving/dp/B08FSJQHP7/ref=sr_1_12?keywords=beer+alcoholic+drinks&qid=1667472794&qu=eyJxc2MiOiIyLjYxIiwicXNhIjoiMC4wMCIsInFzcCI6IjAuMDAifQ%3D%3D&sr=8-12"
      }
    },
    {
      "position": 13,
      "title": "Non-Alcoholic Beer Variety Pack, Beck's, Bitburger, Buckler, Clausthaler Premium and Amber, Coors, St. Pauli Girl, Einbecker, Erdinger, Kaliber, O'Doul's Premium and Amber (Case Of 12)",
      "asin": "B078D6VTC2",
      "link": "https://www.amazon.com/Non-Alcoholic-Beer-Variety-Pack-Clausthaler/dp/B078D6VTC2/ref=sr_1_13?keywords=beer+alcoholic+drinks&qid=1667472794&qu=eyJxc2MiOiIyLjYxIiwicXNhIjoiMC4wMCIsInFzcCI6IjAuMDAifQ%3D%3D&sr=8-13",
      "categories": [
        {
          "name": "All Departments",
          "id": "aps"
        }
      ],
      "image": "https://m.media-amazon.com/images/I/71wfe4BjmeL._AC_UL320_.jpg",
      "rating": 4.3,
      "ratings_total": 110
    },
    {
      "position": 14,
      "title": "Suntory ALL-FREE, Beer-Alternative, Non Alcohol, 6-pack, Ultra-Light, Ultra-Crisp, Ultra-Refreshing, 0.00% Alc. and 0 Calories from Japan,11.8 Fl Oz (Pack of 6)",
      "asin": "B08BVHRPYV",
      "link": "https://www.amazon.com/Suntory-ALL-FREE-Sparkling-Beverage-Calories/dp/B08BVHRPYV/ref=sr_1_14_mod_primary_new?keywords=beer+alcoholic+drinks&qid=1667472794&qu=eyJxc2MiOiIyLjYxIiwicXNhIjoiMC4wMCIsInFzcCI6IjAuMDAifQ%3D%3D&sbo=RZvfv%2F%2FHxDF%2BO5021pAnSA%3D%3D&sr=8-14",
      "categories": [
        {
          "name": "All Departments",
          "id": "aps"
        }
      ],
      "image": "https://m.media-amazon.com/images/I/71bIcWoFC9L._AC_UL320_.jpg",
      "is_prime": true,
      "rating": 3.9,
      "ratings_total": 749,
      "prices": [
        {
          "symbol": "$",
          "value": 19.14,
          "currency": "USD",
          "raw": "$19.14",
          "name": "$19.14"
        },
        {
          "symbol": "$",
          "value": 18.18,
          "currency": "USD",
          "raw": "$18.18",
          "name": "$18.18"
        }
      ],
      "price": {
        "symbol": "$",
        "value": 19.14,
        "currency": "USD",
        "raw": "$19.14",
        "name": "$19.14"
      }
    },
    {
      "position": 15,
      "title": "Q Mixers Premium Ginger Beer: Real Ingredients & Less Sweet, 7.5 Fl oz per can, 24 Cans",
      "asin": "B071KC3846",
      "link": "https://www.amazon.com/Drinks-Ginger-Spectacular-Premium-Mixer/dp/B071KC3846/ref=sr_1_15_mod_primary_new?keywords=beer+alcoholic+drinks&qid=1667472794&qu=eyJxc2MiOiIyLjYxIiwicXNhIjoiMC4wMCIsInFzcCI6IjAuMDAifQ%3D%3D&sbo=RZvfv%2F%2FHxDF%2BO5021pAnSA%3D%3D&sr=8-15",
      "categories": [
        {
          "name": "All Departments",
          "id": "aps"
        }
      ],
      "image": "https://m.media-amazon.com/images/I/61VCQYvYmSS._AC_UL320_.jpg",
      "bestseller": {
        "link": "https://www.amazon.com/gp/bestsellers/grocery/5782446011/ref=sr_bs_14_5782446011_1",
        "category": "Tonic Drinking Water"
      },
      "is_prime": true,
      "rating": 4.6,
      "ratings_total": 8450,
      "prices": [
        {
          "symbol": "$",
          "value": 21.48,
          "currency": "USD",
          "raw": "$21.48",
          "name": "$21.48"
        },
        {
          "symbol": "$",
          "value": 20.41,
          "currency": "USD",
          "raw": "$20.41",
          "name": "$20.41"
        }
      ],
      "price": {
        "symbol": "$",
        "value": 21.48,
        "currency": "USD",
        "raw": "$21.48",
        "name": "$21.48"
      }
    },
    {
      "position": 16,
      "title": "RITUAL ZERO PROOF Rum Alternative | Award-Winning Non-Alcoholic Spirit | 25.4 Fl Oz (750ml) | Only 5 Calories | Sustainably Made in USA | Make Alcohol Free Cocktails",
      "asin": "B08QB3C8S3",
      "link": "https://www.amazon.com/Alternative-Award-Winning-Non-Alcoholic-Calories-Cocktails/dp/B08QB3C8S3/ref=sr_1_16_mod_primary_new?keywords=beer+alcoholic+drinks&qid=1667472794&qu=eyJxc2MiOiIyLjYxIiwicXNhIjoiMC4wMCIsInFzcCI6IjAuMDAifQ%3D%3D&sbo=RZvfv%2F%2FHxDF%2BO5021pAnSA%3D%3D&sr=8-16",
      "categories": [
        {
          "name": "All Departments",
          "id": "aps"
        }
      ],
      "image": "https://m.media-amazon.com/images/I/71zgKhGrxQS._AC_UL320_.jpg",
      "is_prime": true,
      "rating": 3.7,
      "ratings_total": 680,
      "is_small_business": true,
      "prices": [
        {
          "symbol": "$",
          "value": 29.99,
          "currency": "USD",
          "raw": "$29.99",
          "name": "$29.99"
        },
        {
          "symbol": "$",
          "value": 26.99,
          "currency": "USD",
          "raw": "$26.99",
          "name": "$26.99"
        }
      ],
      "price": {
        "symbol": "$",
        "value": 29.99,
        "currency": "USD",
        "raw": "$29.99",
        "name": "$29.99"
      }
    },
    {
      "position": 17,
      "title": "HOP WTR - Sparkling Hop Water - Mango - (12 Pack) - NA Beer, No Calories or Sugar, Low Carb, With Adaptogens and Nootropics for Added Benefits (12 oz Cans)",
      "asin": "B08KRJCKSH",
      "link": "https://www.amazon.com/HOP-WTR-Sparkling-Adaptogens-Nootropics/dp/B08KRJCKSH/ref=sr_1_17_mod_primary_new?keywords=beer+alcoholic+drinks&qid=1667472794&qu=eyJxc2MiOiIyLjYxIiwicXNhIjoiMC4wMCIsInFzcCI6IjAuMDAifQ%3D%3D&sbo=RZvfv%2F%2FHxDF%2BO5021pAnSA%3D%3D&sr=8-17",
      "categories": [
        {
          "name": "All Departments",
          "id": "aps"
        }
      ],
      "image": "https://m.media-amazon.com/images/I/518IXK-6yrL._AC_UL320_.jpg",
      "amazons_choice": {
        "link": "https://www.amazon.com/HOP-WTR-Sparkling-Adaptogens-Nootropics/dp/B08KRJCKSH/ref=ice_ac_b_dpb?keywords=beer+alcoholic+drinks&qid=1667472794&qu=eyJxc2MiOiIyLjYxIiwicXNhIjoiMC4wMCIsInFzcCI6IjAuMDAifQ%3D%3D&sbo=RZvfv%2F%2FHxDF%2BO5021pAnSA%3D%3D&sr=8-17",
        "keywords": "beer alcoholic drinks"
      },
      "coupon": {
        "badge_text": "Save 15%",
        "text": "with coupon"
      },
      "is_prime": true,
      "rating": 4.5,
      "ratings_total": 227,
      "is_small_business": true,
      "prices": [
        {
          "symbol": "$",
          "value": 36.99,
          "currency": "USD",
          "raw": "$36.99",
          "name": "$36.99"
        },
        {
          "symbol": "$",
          "value": 33.29,
          "currency": "USD",
          "raw": "$33.29",
          "name": "$33.29"
        }
      ],
      "price": {
        "symbol": "$",
        "value": 36.99,
        "currency": "USD",
        "raw": "$36.99",
        "name": "$36.99"
      }
    },
    {
      "position": 18,
      "title": "Recess Mood Magnesium Supplement Drink Calming Beverage, 12 Ounce, Pack of 12 (Variety Pack, 12 Pack) *Original Flavors*",
      "asin": "B08WPWBCZ3",
      "link": "https://www.amazon.com/Recess-Magnesium-Supplement-Drink-Beverage/dp/B08WPWBCZ3/ref=sr_1_18_mod_primary_new?keywords=beer+alcoholic+drinks&qid=1667472794&qu=eyJxc2MiOiIyLjYxIiwicXNhIjoiMC4wMCIsInFzcCI6IjAuMDAifQ%3D%3D&sbo=RZvfv%2F%2FHxDF%2BO5021pAnSA%3D%3D&sr=8-18",
      "categories": [
        {
          "name": "All Departments",
          "id": "aps"
        }
      ],
      "image": "https://m.media-amazon.com/images/I/715R9UbOnLS._AC_UL320_.jpg",
      "is_prime": true,
      "rating": 4.2,
      "ratings_total": 549,
      "is_small_business": true,
      "prices": [
        {
          "symbol": "$",
          "value": 41.99,
          "currency": "USD",
          "raw": "$41.99",
          "name": "$41.99"
        },
        {
          "symbol": "$",
          "value": 37.79,
          "currency": "USD",
          "raw": "$37.79",
          "name": "$37.79"
        }
      ],
      "price": {
        "symbol": "$",
        "value": 41.99,
        "currency": "USD",
        "raw": "$41.99",
        "name": "$41.99"
      }
    },
    {
      "position": 19,
      "title": "** The Official Spirit of Dry January ** Lyre's Non Alcoholic Spirits Mixed (Amalfi Spritz/G&T/Classico) - Ready To Drink Spritz, Sparkling, Gin & Tonic Cocktails - Pack of 12 (3 Packs of 4 X 8.5 Fl Oz)",
      "asin": "B08XH6KCY3",
      "link": "https://www.amazon.com/Lyres-Non-Alcoholic-Amalfi-Spritz-Classico/dp/B08XH6KCY3/ref=sr_1_19?keywords=beer+alcoholic+drinks&qid=1667472794&qu=eyJxc2MiOiIyLjYxIiwicXNhIjoiMC4wMCIsInFzcCI6IjAuMDAifQ%3D%3D&sr=8-19",
      "categories": [
        {
          "name": "All Departments",
          "id": "aps"
        }
      ],
      "image": "https://m.media-amazon.com/images/I/81xD6J-M98L._AC_UL320_.jpg",
      "rating": 4.2,
      "ratings_total": 230,
      "is_small_business": true,
      "prices": [
        {
          "symbol": "$",
          "value": 44.97,
          "currency": "USD",
          "raw": "$44.97",
          "name": "$44.97",
          "asin": "B08XH6KCY3",
          "link": "https://www.amazon.com/Lyres-Non-Alcoholic-Amalfi-Spritz-Classico/dp/B08XH6KCY3/ref=sr_1_19?keywords=beer+alcoholic+drinks&qid=1667472794&qu=eyJxc2MiOiIyLjYxIiwicXNhIjoiMC4wMCIsInFzcCI6IjAuMDAifQ%3D%3D&sr=8-19"
        }
      ],
      "price": {
        "symbol": "$",
        "value": 44.97,
        "currency": "USD",
        "raw": "$44.97",
        "name": "$44.97",
        "asin": "B08XH6KCY3",
        "link": "https://www.amazon.com/Lyres-Non-Alcoholic-Amalfi-Spritz-Classico/dp/B08XH6KCY3/ref=sr_1_19?keywords=beer+alcoholic+drinks&qid=1667472794&qu=eyJxc2MiOiIyLjYxIiwicXNhIjoiMC4wMCIsInFzcCI6IjAuMDAifQ%3D%3D&sr=8-19"
      }
    },
    {
      "position": 20,
      "title": "**The Official Drink of Sober October** - Mocktails Uniquely Crafted Alcohol Free Variety Pack | Non-Alcoholic Cocktail, Low Calorie, Non-GMO, Vegan Alternative | 6.8 Fluid Ounce (Pack of 12)",
      "asin": "B07KB8KGS9",
      "link": "https://www.amazon.com/Official-Drink-Sober-October-Non-Alcoholic/dp/B07KB8KGS9/ref=sr_1_20_mod_primary_new?keywords=beer+alcoholic+drinks&qid=1667472794&qu=eyJxc2MiOiIyLjYxIiwicXNhIjoiMC4wMCIsInFzcCI6IjAuMDAifQ%3D%3D&sbo=RZvfv%2F%2FHxDF%2BO5021pAnSA%3D%3D&sr=8-20",
      "categories": [
        {
          "name": "All Departments",
          "id": "aps"
        }
      ],
      "image": "https://m.media-amazon.com/images/I/71hR+sve1+L._AC_UL320_.jpg",
      "is_prime": true,
      "rating": 3.7,
      "ratings_total": 516,
      "is_small_business": true,
      "prices": [
        {
          "symbol": "$",
          "value": 39.99,
          "currency": "USD",
          "raw": "$39.99",
          "name": "$39.99"
        },
        {
          "symbol": "$",
          "value": 35.99,
          "currency": "USD",
          "raw": "$35.99",
          "name": "$35.99"
        }
      ],
      "price": {
        "symbol": "$",
        "value": 39.99,
        "currency": "USD",
        "raw": "$39.99",
        "name": "$39.99"
      }
    },
    {
      "position": 21,
      "title": "RITUAL ZERO PROOF Whiskey Alternative | Award-Winning Non-Alcoholic Spirit | 25.4 Fl Oz (750ml) | Only 5 Calories | Sustainably Made in USA | Make Delicious Alcohol Free Cocktails",
      "asin": "B07VPWR7YY",
      "link": "https://www.amazon.com/Alternative-Award-Winning-Non-Alcoholic-Delicious-Cocktails/dp/B07VPWR7YY/ref=sr_1_21_mod_primary_new?keywords=beer+alcoholic+drinks&qid=1667472794&qu=eyJxc2MiOiIyLjYxIiwicXNhIjoiMC4wMCIsInFzcCI6IjAuMDAifQ%3D%3D&sbo=RZvfv%2F%2FHxDF%2BO5021pAnSA%3D%3D&sr=8-21",
      "categories": [
        {
          "name": "All Departments",
          "id": "aps"
        }
      ],
      "image": "https://m.media-amazon.com/images/I/71ToBzbogQS._AC_UL320_.jpg",
      "is_prime": true,
      "rating": 2.9,
      "ratings_total": 3663,
      "is_small_business": true,
      "prices": [
        {
          "symbol": "$",
          "value": 29.99,
          "currency": "USD",
          "raw": "$29.99",
          "name": "$29.99"
        },
        {
          "symbol": "$",
          "value": 26.99,
          "currency": "USD",
          "raw": "$26.99",
          "name": "$26.99"
        }
      ],
      "price": {
        "symbol": "$",
        "value": 29.99,
        "currency": "USD",
        "raw": "$29.99",
        "name": "$29.99"
      }
    },
    {
      "position": 22,
      "title": "Zenify Zero Sugar All Natural Sparkling Calming Stress Relief Beverage, Formula with L-Theanine, GABA, Vitamin B6, and Glycine, Alcohol Replacement Drink, 12 Fl Ounce (Pack of 12)",
      "asin": "B073XVY6BB",
      "link": "https://www.amazon.com/Zenify-Natural-Sparkling-Calming-Beverage/dp/B073XVY6BB/ref=sr_1_22_mod_primary_new?keywords=beer+alcoholic+drinks&qid=1667472794&qu=eyJxc2MiOiIyLjYxIiwicXNhIjoiMC4wMCIsInFzcCI6IjAuMDAifQ%3D%3D&sbo=RZvfv%2F%2FHxDF%2BO5021pAnSA%3D%3D&sr=8-22",
      "categories": [
        {
          "name": "All Departments",
          "id": "aps"
        }
      ],
      "image": "https://m.media-amazon.com/images/I/714+LRGIlPL._AC_UL320_.jpg",
      "is_prime": true,
      "rating": 4.2,
      "ratings_total": 1755,
      "prices": [
        {
          "symbol": "$",
          "value": 29.99,
          "currency": "USD",
          "raw": "$29.99",
          "name": "$29.99"
        },
        {
          "symbol": "$",
          "value": 28.49,
          "currency": "USD",
          "raw": "$28.49",
          "name": "$28.49"
        }
      ],
      "price": {
        "symbol": "$",
        "value": 29.99,
        "currency": "USD",
        "raw": "$29.99",
        "name": "$29.99"
      }
    },
    {
      "position": 23,
      "title": "HOP WTR - Sparkling Hop Water - Classic (12 Pack) - NA Beer, No Calories or Sugar, Low Carb, With Adaptogens and Nootropics for Added Benefits (12 oz Cans)",
      "asin": "B08KRWTHW5",
      "link": "https://www.amazon.com/HOP-WTR-Sparkling-Adaptogens-Nootropics/dp/B08KRWTHW5/ref=sr_1_23_mod_primary_new?keywords=beer+alcoholic+drinks&qid=1667472794&qu=eyJxc2MiOiIyLjYxIiwicXNhIjoiMC4wMCIsInFzcCI6IjAuMDAifQ%3D%3D&sbo=RZvfv%2F%2FHxDF%2BO5021pAnSA%3D%3D&sr=8-23",
      "categories": [
        {
          "name": "All Departments",
          "id": "aps"
        }
      ],
      "image": "https://m.media-amazon.com/images/I/511LPD+qbyL._AC_UL320_.jpg",
      "coupon": {
        "badge_text": "Save 15%",
        "text": "with coupon"
      },
      "is_prime": true,
      "rating": 4.1,
      "ratings_total": 181,
      "is_small_business": true,
      "prices": [
        {
          "symbol": "$",
          "value": 36,
          "currency": "USD",
          "raw": "$36.00",
          "name": "$36.00"
        },
        {
          "symbol": "$",
          "value": 32.4,
          "currency": "USD",
          "raw": "$32.40",
          "name": "$32.40"
        }
      ],
      "price": {
        "symbol": "$",
        "value": 36,
        "currency": "USD",
        "raw": "$36.00",
        "name": "$36.00"
      }
    },
    {
      "position": 24,
      "title": "MONDAY Zero Alcohol Whiskey – An Award Winning Non-Alcoholic Spirit with Zero Carbs, No Sugar, 0 Calories - 750ml",
      "asin": "B0949WND5C",
      "link": "https://www.amazon.com/MONDAY-Zero-Alcohol-Whiskey-Non-Alcoholic/dp/B0949WND5C/ref=sr_1_24_mod_primary_new?keywords=beer+alcoholic+drinks&qid=1667472794&qu=eyJxc2MiOiIyLjYxIiwicXNhIjoiMC4wMCIsInFzcCI6IjAuMDAifQ%3D%3D&sbo=RZvfv%2F%2FHxDF%2BO5021pAnSA%3D%3D&sr=8-24",
      "categories": [
        {
          "name": "All Departments",
          "id": "aps"
        }
      ],
      "image": "https://m.media-amazon.com/images/I/81u8CKWme8L._AC_UL320_.jpg",
      "is_prime": true,
      "rating": 3,
      "ratings_total": 323,
      "is_small_business": true,
      "prices": [
        {
          "symbol": "$",
          "value": 44.99,
          "currency": "USD",
          "raw": "$44.99",
          "name": "$44.99"
        },
        {
          "symbol": "$",
          "value": 40.49,
          "currency": "USD",
          "raw": "$40.49",
          "name": "$40.49"
        }
      ],
      "price": {
        "symbol": "$",
        "value": 44.99,
        "currency": "USD",
        "raw": "$44.99",
        "name": "$44.99"
      }
    },
    {
      "position": 25,
      "title": "BrewDog 24 Mixed Non-Alcoholic Pack | Includes Nanny, Elvis, Hazy, & Punk | 12oz Cans",
      "asin": "B08FTH8VD6",
      "link": "https://www.amazon.com/BrewDog-Mixed-Non-Alcoholic-Hoppy-Robust/dp/B08FTH8VD6/ref=sr_1_25?keywords=beer+alcoholic+drinks&qid=1667472794&qu=eyJxc2MiOiIyLjYxIiwicXNhIjoiMC4wMCIsInFzcCI6IjAuMDAifQ%3D%3D&sr=8-25",
      "categories": [
        {
          "name": "All Departments",
          "id": "aps"
        }
      ],
      "image": "https://m.media-amazon.com/images/I/71Ht6T2ec3L._AC_UL320_.jpg",
      "rating": 4.4,
      "ratings_total": 198,
      "prices": [
        {
          "symbol": "$",
          "value": 48.95,
          "currency": "USD",
          "raw": "$48.95",
          "name": "$48.95",
          "asin": "B08FTH8VD6",
          "link": "https://www.amazon.com/BrewDog-Mixed-Non-Alcoholic-Hoppy-Robust/dp/B08FTH8VD6/ref=sr_1_25?keywords=beer+alcoholic+drinks&qid=1667472794&qu=eyJxc2MiOiIyLjYxIiwicXNhIjoiMC4wMCIsInFzcCI6IjAuMDAifQ%3D%3D&sr=8-25"
        }
      ],
      "price": {
        "symbol": "$",
        "value": 48.95,
        "currency": "USD",
        "raw": "$48.95",
        "name": "$48.95",
        "asin": "B08FTH8VD6",
        "link": "https://www.amazon.com/BrewDog-Mixed-Non-Alcoholic-Hoppy-Robust/dp/B08FTH8VD6/ref=sr_1_25?keywords=beer+alcoholic+drinks&qid=1667472794&qu=eyJxc2MiOiIyLjYxIiwicXNhIjoiMC4wMCIsInFzcCI6IjAuMDAifQ%3D%3D&sr=8-25"
      }
    },
    {
      "position": 26,
      "title": "Free Spirits | The Spirit of Bourbon | Award Winning Non-Alcoholic Spirit for Cocktails | Oak-Caramel Nose, Only 5 Calories, Vegan & Gluten-Free with Mood Lifting Vitamins | 750 ml",
      "asin": "B08N9RCRCG",
      "link": "https://www.amazon.com/Spirits-Bourbon-Non-Alcoholic-Oak-Caramel-Velvety-Smooth/dp/B08N9RCRCG/ref=sr_1_26_mod_primary_new?keywords=beer+alcoholic+drinks&qid=1667472794&qu=eyJxc2MiOiIyLjYxIiwicXNhIjoiMC4wMCIsInFzcCI6IjAuMDAifQ%3D%3D&sbo=RZvfv%2F%2FHxDF%2BO5021pAnSA%3D%3D&sr=8-26",
      "categories": [
        {
          "name": "All Departments",
          "id": "aps"
        }
      ],
      "image": "https://m.media-amazon.com/images/I/61CvLENw6BL._AC_UL320_.jpg",
      "is_prime": true,
      "rating": 2.9,
      "ratings_total": 322,
      "is_small_business": true,
      "prices": [
        {
          "symbol": "$",
          "value": 36.99,
          "currency": "USD",
          "raw": "$36.99",
          "name": "$36.99"
        },
        {
          "symbol": "$",
          "value": 33.29,
          "currency": "USD",
          "raw": "$33.29",
          "name": "$33.29"
        }
      ],
      "price": {
        "symbol": "$",
        "value": 36.99,
        "currency": "USD",
        "raw": "$36.99",
        "name": "$36.99"
      }
    },
    {
      "position": 27,
      "title": "Sober Carpenter NA Craft Beer - Blonde Ale Non Alcoholic 12 pack /16 oz Cans of Low-Calorie, Award Winning, All Natural Ingredients for a Great Tasting Drink",
      "asin": "B09YVS5CS6",
      "link": "https://www.amazon.com/Sober-Carpenter-Craft-Beer-Low-Calorie/dp/B09YVS5CS6/ref=sr_1_27?keywords=beer+alcoholic+drinks&qid=1667472794&qu=eyJxc2MiOiIyLjYxIiwicXNhIjoiMC4wMCIsInFzcCI6IjAuMDAifQ%3D%3D&sr=8-27",
      "categories": [
        {
          "name": "All Departments",
          "id": "aps"
        }
      ],
      "image": "https://m.media-amazon.com/images/I/81r8KebshGL._AC_UL320_.jpg",
      "coupon": {
        "badge_text": "Save 11%",
        "text": "with coupon"
      },
      "is_prime": true,
      "rating": 5,
      "ratings_total": 1,
      "prices": [
        {
          "symbol": "$",
          "value": 39.99,
          "currency": "USD",
          "raw": "$39.99",
          "name": "$39.99",
          "asin": "B09YVS5CS6",
          "link": "https://www.amazon.com/Sober-Carpenter-Craft-Beer-Low-Calorie/dp/B09YVS5CS6/ref=sr_1_27?keywords=beer+alcoholic+drinks&qid=1667472794&qu=eyJxc2MiOiIyLjYxIiwicXNhIjoiMC4wMCIsInFzcCI6IjAuMDAifQ%3D%3D&sr=8-27"
        }
      ],
      "price": {
        "symbol": "$",
        "value": 39.99,
        "currency": "USD",
        "raw": "$39.99",
        "name": "$39.99",
        "asin": "B09YVS5CS6",
        "link": "https://www.amazon.com/Sober-Carpenter-Craft-Beer-Low-Calorie/dp/B09YVS5CS6/ref=sr_1_27?keywords=beer+alcoholic+drinks&qid=1667472794&qu=eyJxc2MiOiIyLjYxIiwicXNhIjoiMC4wMCIsInFzcCI6IjAuMDAifQ%3D%3D&sr=8-27"
      }
    },
    {
      "position": 28,
      "title": "Flying Cauldron Butterscotch Beer 12oz (Pack of 6) Bundle with PrimeTime Direct Keychain Bottle Opener in a PTD Sealed Box",
      "asin": "B082J5KXLG",
      "link": "https://www.amazon.com/Flying-Cauldron-Butterscotch-PrimeTime-Keychain/dp/B082J5KXLG/ref=sr_1_28?keywords=beer+alcoholic+drinks&qid=1667472794&qu=eyJxc2MiOiIyLjYxIiwicXNhIjoiMC4wMCIsInFzcCI6IjAuMDAifQ%3D%3D&sr=8-28",
      "categories": [
        {
          "name": "All Departments",
          "id": "aps"
        }
      ],
      "image": "https://m.media-amazon.com/images/I/91j8hyLfV8L._AC_UL320_.jpg",
      "is_prime": true,
      "rating": 4.4,
      "ratings_total": 778,
      "prices": [
        {
          "symbol": "$",
          "value": 31.98,
          "currency": "USD",
          "raw": "$31.98",
          "name": "$31.98",
          "asin": "B082J5KXLG",
          "link": "https://www.amazon.com/Flying-Cauldron-Butterscotch-PrimeTime-Keychain/dp/B082J5KXLG/ref=sr_1_28?keywords=beer+alcoholic+drinks&qid=1667472794&qu=eyJxc2MiOiIyLjYxIiwicXNhIjoiMC4wMCIsInFzcCI6IjAuMDAifQ%3D%3D&sr=8-28"
        }
      ],
      "price": {
        "symbol": "$",
        "value": 31.98,
        "currency": "USD",
        "raw": "$31.98",
        "name": "$31.98",
        "asin": "B082J5KXLG",
        "link": "https://www.amazon.com/Flying-Cauldron-Butterscotch-PrimeTime-Keychain/dp/B082J5KXLG/ref=sr_1_28?keywords=beer+alcoholic+drinks&qid=1667472794&qu=eyJxc2MiOiIyLjYxIiwicXNhIjoiMC4wMCIsInFzcCI6IjAuMDAifQ%3D%3D&sr=8-28"
      }
    },
    {
      "position": 29,
      "title": "Coors Edge Domestic, NA (Non-Alcoholic) Beer, Low Cal & Carb - 12 Fl Oz, (12 Glass Bottles)",
      "asin": "B091JCHQK8",
      "link": "https://www.amazon.com/Coors-Edge-Domestic-Non-Alcoholic-Beer/dp/B091JCHQK8/ref=sr_1_29?keywords=beer+alcoholic+drinks&qid=1667472794&qu=eyJxc2MiOiIyLjYxIiwicXNhIjoiMC4wMCIsInFzcCI6IjAuMDAifQ%3D%3D&sr=8-29",
      "categories": [
        {
          "name": "All Departments",
          "id": "aps"
        }
      ],
      "image": "https://m.media-amazon.com/images/I/61YLtLIuLqL._AC_UL320_.jpg",
      "rating": 4.7,
      "ratings_total": 4,
      "prices": [
        {
          "symbol": "$",
          "value": 49.98,
          "currency": "USD",
          "raw": "$49.98",
          "name": "$49.98",
          "asin": "B091JCHQK8",
          "link": "https://www.amazon.com/Coors-Edge-Domestic-Non-Alcoholic-Beer/dp/B091JCHQK8/ref=sr_1_29?keywords=beer+alcoholic+drinks&qid=1667472794&qu=eyJxc2MiOiIyLjYxIiwicXNhIjoiMC4wMCIsInFzcCI6IjAuMDAifQ%3D%3D&sr=8-29"
        }
      ],
      "price": {
        "symbol": "$",
        "value": 49.98,
        "currency": "USD",
        "raw": "$49.98",
        "name": "$49.98",
        "asin": "B091JCHQK8",
        "link": "https://www.amazon.com/Coors-Edge-Domestic-Non-Alcoholic-Beer/dp/B091JCHQK8/ref=sr_1_29?keywords=beer+alcoholic+drinks&qid=1667472794&qu=eyJxc2MiOiIyLjYxIiwicXNhIjoiMC4wMCIsInFzcCI6IjAuMDAifQ%3D%3D&sr=8-29"
      }
    },
    {
      "position": 30,
      "title": "DRY Non-Alcoholic Botanical Bubbly |Ginger | Sparkling and ready to sip or Use as a Mocktail Mixer |Less Sweet, All Natural Ingredients, Non-GMO | Sophisticatedly zero-proof, 12 Fl Oz (Pack of 12)",
      "asin": "B0712225D5",
      "link": "https://www.amazon.com/DRY-Sparkling-Ginger-Soda-Count/dp/B0712225D5/ref=sr_1_30_mod_primary_new?keywords=beer+alcoholic+drinks&qid=1667472794&qu=eyJxc2MiOiIyLjYxIiwicXNhIjoiMC4wMCIsInFzcCI6IjAuMDAifQ%3D%3D&sbo=RZvfv%2F%2FHxDF%2BO5021pAnSA%3D%3D&sr=8-30",
      "categories": [
        {
          "name": "All Departments",
          "id": "aps"
        }
      ],
      "image": "https://m.media-amazon.com/images/I/715pFl8YTfL._AC_UL320_.jpg",
      "is_prime": true,
      "rating": 4.4,
      "ratings_total": 1075,
      "prices": [
        {
          "symbol": "$",
          "value": 29.99,
          "currency": "USD",
          "raw": "$29.99",
          "name": "$29.99"
        },
        {
          "symbol": "$",
          "value": 28.49,
          "currency": "USD",
          "raw": "$28.49",
          "name": "$28.49"
        }
      ],
      "price": {
        "symbol": "$",
        "value": 29.99,
        "currency": "USD",
        "raw": "$29.99",
        "name": "$29.99"
      }
    },
    {
      "position": 31,
      "title": "Bundaberg Ginger Beer, 6.8 fl oz Cans, (24 Pack)",
      "asin": "B08DBF7XP6",
      "link": "https://www.amazon.com/Bundaberg-Ginger-Beer-Cans-Pack/dp/B08DBF7XP6/ref=sr_1_31_mod_primary_new?keywords=beer+alcoholic+drinks&qid=1667472794&qu=eyJxc2MiOiIyLjYxIiwicXNhIjoiMC4wMCIsInFzcCI6IjAuMDAifQ%3D%3D&sbo=RZvfv%2F%2FHxDF%2BO5021pAnSA%3D%3D&sr=8-31",
      "categories": [
        {
          "name": "All Departments",
          "id": "aps"
        }
      ],
      "image": "https://m.media-amazon.com/images/I/91wGUDjZvOL._AC_UL320_.jpg",
      "is_prime": true,
      "rating": 4.6,
      "ratings_total": 1372,
      "prices": [
        {
          "symbol": "$",
          "value": 48.5,
          "currency": "USD",
          "raw": "$48.50",
          "name": "$48.50"
        },
        {
          "symbol": "$",
          "value": 46.08,
          "currency": "USD",
          "raw": "$46.08",
          "name": "$46.08"
        }
      ],
      "price": {
        "symbol": "$",
        "value": 48.5,
        "currency": "USD",
        "raw": "$48.50",
        "name": "$48.50"
      }
    },
    {
      "position": 32,
      "title": "MONDAY Zero Alcohol Gin – An Award Winning Non-Alcoholic Spirit with Zero Carbs, No Sugar, 0 Calories - 750ml",
      "asin": "B083JN9J8M",
      "link": "https://www.amazon.com/MONDAY-Zero-Alcohol-Gin-Non-Alcoholic/dp/B083JN9J8M/ref=sr_1_32_mod_primary_new?keywords=beer+alcoholic+drinks&qid=1667472794&qu=eyJxc2MiOiIyLjYxIiwicXNhIjoiMC4wMCIsInFzcCI6IjAuMDAifQ%3D%3D&sbo=RZvfv%2F%2FHxDF%2BO5021pAnSA%3D%3D&sr=8-32",
      "categories": [
        {
          "name": "All Departments",
          "id": "aps"
        }
      ],
      "image": "https://m.media-amazon.com/images/I/71OxVdKKYeL._AC_UL320_.jpg",
      "is_prime": true,
      "rating": 3.6,
      "ratings_total": 1717,
      "is_small_business": true,
      "prices": [
        {
          "symbol": "$",
          "value": 39.99,
          "currency": "USD",
          "raw": "$39.99",
          "name": "$39.99"
        },
        {
          "symbol": "$",
          "value": 35.99,
          "currency": "USD",
          "raw": "$35.99",
          "name": "$35.99"
        }
      ],
      "price": {
        "symbol": "$",
        "value": 39.99,
        "currency": "USD",
        "raw": "$39.99",
        "name": "$39.99"
      }
    },
    {
      "position": 33,
      "title": "Athletic Brewing Company Craft Non-Alcoholic Beer - 24 Pack x 12 Fl Oz Cans - Cerveza Atletica - Low-Calorie, Award Winning - Rich Aroma and Flavor Balanced with Light Spicy and Floral Notes",
      "asin": "B08J5N8WX8",
      "link": "https://www.amazon.com/Athletic-Brewing-Company-Craft-Low-Calorie/dp/B08J5N8WX8/ref=sr_1_33?keywords=beer+alcoholic+drinks&qid=1667472794&qu=eyJxc2MiOiIyLjYxIiwicXNhIjoiMC4wMCIsInFzcCI6IjAuMDAifQ%3D%3D&sr=8-33",
      "categories": [
        {
          "name": "All Departments",
          "id": "aps"
        }
      ],
      "image": "https://m.media-amazon.com/images/I/61Cp7OSv4TL._AC_UL320_.jpg",
      "rating": 4.4,
      "ratings_total": 39
    },
    {
      "position": 34,
      "title": "Flying Cauldron Butterscotch Beer (Pack of 6)",
      "asin": "B00787YLJE",
      "link": "https://www.amazon.com/Flying-Cauldron-Butterscotch-Beer-Pack/dp/B00787YLJE/ref=sr_1_34?keywords=beer+alcoholic+drinks&qid=1667472794&qu=eyJxc2MiOiIyLjYxIiwicXNhIjoiMC4wMCIsInFzcCI6IjAuMDAifQ%3D%3D&sr=8-34",
      "availability": {
        "raw": "Only 6 left in stock - order soon."
      },
      "categories": [
        {
          "name": "All Departments",
          "id": "aps"
        }
      ],
      "image": "https://m.media-amazon.com/images/I/713KXxd0UcL._AC_UL320_.jpg",
      "rating": 4.1,
      "ratings_total": 647,
      "is_small_business": true,
      "prices": [
        {
          "symbol": "$",
          "value": 21.99,
          "currency": "USD",
          "raw": "$21.99",
          "name": "$21.99",
          "is_primary": true
        },
        {
          "symbol": "$",
          "value": 24.88,
          "currency": "USD",
          "raw": "$24.88",
          "name": "$21.99",
          "is_rrp": true
        }
      ],
      "price": {
        "symbol": "$",
        "value": 21.99,
        "currency": "USD",
        "raw": "$21.99",
        "name": "$21.99",
        "is_primary": true
      }
    },
    {
      "position": 35,
      "title": "Gruvi Non-Alcoholic Beer Variety Pack, 12-Pack, IPA, Stout, Pale Ale, <0.5% ABV, Zero Alcohol Beer, NA Beer",
      "asin": "B09PHWM5RT",
      "link": "https://www.amazon.com/Gruvi-Non-Alcoholic-Variety-12-Pack-Alcohol/dp/B09PHWM5RT/ref=sr_1_35?keywords=beer+alcoholic+drinks&qid=1667472794&qu=eyJxc2MiOiIyLjYxIiwicXNhIjoiMC4wMCIsInFzcCI6IjAuMDAifQ%3D%3D&sr=8-35",
      "categories": [
        {
          "name": "All Departments",
          "id": "aps"
        }
      ],
      "image": "https://m.media-amazon.com/images/I/81t9omWlO4L._AC_UL320_.jpg",
      "rating": 4.3,
      "ratings_total": 9,
      "prices": [
        {
          "symbol": "$",
          "value": 29.99,
          "currency": "USD",
          "raw": "$29.99",
          "name": "$29.99",
          "asin": "B09PHWM5RT",
          "link": "https://www.amazon.com/Gruvi-Non-Alcoholic-Variety-12-Pack-Alcohol/dp/B09PHWM5RT/ref=sr_1_35?keywords=beer+alcoholic+drinks&qid=1667472794&qu=eyJxc2MiOiIyLjYxIiwicXNhIjoiMC4wMCIsInFzcCI6IjAuMDAifQ%3D%3D&sr=8-35"
        }
      ],
      "price": {
        "symbol": "$",
        "value": 29.99,
        "currency": "USD",
        "raw": "$29.99",
        "name": "$29.99",
        "asin": "B09PHWM5RT",
        "link": "https://www.amazon.com/Gruvi-Non-Alcoholic-Variety-12-Pack-Alcohol/dp/B09PHWM5RT/ref=sr_1_35?keywords=beer+alcoholic+drinks&qid=1667472794&qu=eyJxc2MiOiIyLjYxIiwicXNhIjoiMC4wMCIsInFzcCI6IjAuMDAifQ%3D%3D&sr=8-35"
      }
    },
    {
      "position": 36,
      "title": "Flying Cauldron Butterscotch Beer 12 Oz 4 Bottles",
      "asin": "B01426M3VQ",
      "link": "https://www.amazon.com/Flying-Cauldron-Butterscotch-Beer-Bottles/dp/B01426M3VQ/ref=sr_1_36_mod_primary_new?keywords=beer+alcoholic+drinks&qid=1667472794&qu=eyJxc2MiOiIyLjYxIiwicXNhIjoiMC4wMCIsInFzcCI6IjAuMDAifQ%3D%3D&sbo=RZvfv%2F%2FHxDF%2BO5021pAnSA%3D%3D&sr=8-36",
      "availability": {
        "raw": "Only 7 left in stock - order soon."
      },
      "categories": [
        {
          "name": "All Departments",
          "id": "aps"
        }
      ],
      "image": "https://m.media-amazon.com/images/I/613bXIPqBjL._AC_UL320_.jpg",
      "is_prime": true,
      "rating": 4.1,
      "ratings_total": 445,
      "prices": [
        {
          "raw": "Another way to buy",
          "name": "$18.32",
          "asin": "B01426M3VQ",
          "link": "https://www.amazon.com/Flying-Cauldron-Butterscotch-Beer-Bottles/dp/B01426M3VQ/ref=sr_1_36_mod_primary_new?keywords=beer+alcoholic+drinks&qid=1667472794&qu=eyJxc2MiOiIyLjYxIiwicXNhIjoiMC4wMCIsInFzcCI6IjAuMDAifQ%3D%3D&sbo=RZvfv%2F%2FHxDF%2BO5021pAnSA%3D%3D&sr=8-36"
        },
        {
          "symbol": "$",
          "value": 18.32,
          "currency": "USD",
          "raw": "$18.32",
          "name": "$18.32"
        },
        {
          "symbol": "$",
          "value": 19.82,
          "currency": "USD",
          "raw": "$19.82",
          "name": "$19.82"
        }
      ],
      "price": {
        "raw": "Another way to buy",
        "name": "$18.32",
        "asin": "B01426M3VQ",
        "link": "https://www.amazon.com/Flying-Cauldron-Butterscotch-Beer-Bottles/dp/B01426M3VQ/ref=sr_1_36_mod_primary_new?keywords=beer+alcoholic+drinks&qid=1667472794&qu=eyJxc2MiOiIyLjYxIiwicXNhIjoiMC4wMCIsInFzcCI6IjAuMDAifQ%3D%3D&sbo=RZvfv%2F%2FHxDF%2BO5021pAnSA%3D%3D&sr=8-36"
      }
    },
    {
      "position": 37,
      "title": "Heineken Non-alcoholic Beer, 12 Oz, 6 Ct",
      "asin": "B07KSSJW94",
      "link": "https://www.amazon.com/Heineken-Non-alcoholic-Beer-12-Oz/dp/B07KSSJW94/ref=sr_1_37?keywords=beer+alcoholic+drinks&qid=1667472794&qu=eyJxc2MiOiIyLjYxIiwicXNhIjoiMC4wMCIsInFzcCI6IjAuMDAifQ%3D%3D&sr=8-37",
      "categories": [
        {
          "name": "All Departments",
          "id": "aps"
        }
      ],
      "image": "https://m.media-amazon.com/images/I/81pYeBg5J4L._AC_UL320_.jpg",
      "rating": 4.7,
      "ratings_total": 420,
      "prices": [
        {
          "symbol": "$",
          "value": 9.99,
          "currency": "USD",
          "raw": "$9.99",
          "name": "$9.99",
          "asin": "B07KSSJW94",
          "link": "https://www.amazon.com/Heineken-Non-alcoholic-Beer-12-Oz/dp/B07KSSJW94/ref=sr_1_37?keywords=beer+alcoholic+drinks&qid=1667472794&qu=eyJxc2MiOiIyLjYxIiwicXNhIjoiMC4wMCIsInFzcCI6IjAuMDAifQ%3D%3D&sr=8-37"
        }
      ],
      "price": {
        "symbol": "$",
        "value": 9.99,
        "currency": "USD",
        "raw": "$9.99",
        "name": "$9.99",
        "asin": "B07KSSJW94",
        "link": "https://www.amazon.com/Heineken-Non-alcoholic-Beer-12-Oz/dp/B07KSSJW94/ref=sr_1_37?keywords=beer+alcoholic+drinks&qid=1667472794&qu=eyJxc2MiOiIyLjYxIiwicXNhIjoiMC4wMCIsInFzcCI6IjAuMDAifQ%3D%3D&sr=8-37"
      }
    },
    {
      "position": 38,
      "title": "RITUAL ZERO PROOF Tequila Alternative | Award-Winning Non-Alcoholic Spirit | 25.4 Fl Oz (750ml) | Zero Calories | Sustainably Made in USA | Make Delicious Alcohol Free Cocktails",
      "asin": "B0866DCX32",
      "link": "https://www.amazon.com/RITUAL-Tequila-Alternative-Award-Winning-Non-Alcoholic/dp/B0866DCX32/ref=sr_1_38_mod_primary_new?keywords=beer+alcoholic+drinks&qid=1667472794&qu=eyJxc2MiOiIyLjYxIiwicXNhIjoiMC4wMCIsInFzcCI6IjAuMDAifQ%3D%3D&sbo=RZvfv%2F%2FHxDF%2BO5021pAnSA%3D%3D&sr=8-38",
      "categories": [
        {
          "name": "All Departments",
          "id": "aps"
        }
      ],
      "image": "https://m.media-amazon.com/images/I/71jdQ57tn1S._AC_UL320_.jpg",
      "is_prime": true,
      "rating": 3.6,
      "ratings_total": 3238,
      "is_small_business": true,
      "prices": [
        {
          "symbol": "$",
          "value": 29.99,
          "currency": "USD",
          "raw": "$29.99",
          "name": "$29.99"
        },
        {
          "symbol": "$",
          "value": 26.99,
          "currency": "USD",
          "raw": "$26.99",
          "name": "$26.99"
        }
      ],
      "price": {
        "symbol": "$",
        "value": 29.99,
        "currency": "USD",
        "raw": "$29.99",
        "name": "$29.99"
      }
    },
    {
      "position": 39,
      "title": "Real Non-Alcoholic Cocktails | SPIRITY COCKTAILS | Award Winning | Crafted with Spirits Distilled From Tea | Mindful Mule | 4-pack",
      "asin": "B088KP5BX7",
      "link": "https://www.amazon.com/Spirity-Cocktails-Non-Alcoholic-Cocktail-Distilled/dp/B088KP5BX7/ref=sr_1_39_mod_primary_new?keywords=beer+alcoholic+drinks&qid=1667472794&qu=eyJxc2MiOiIyLjYxIiwicXNhIjoiMC4wMCIsInFzcCI6IjAuMDAifQ%3D%3D&sbo=RZvfv%2F%2FHxDF%2BO5021pAnSA%3D%3D&sr=8-39",
      "categories": [
        {
          "name": "All Departments",
          "id": "aps"
        }
      ],
      "image": "https://m.media-amazon.com/images/I/8146292pxXL._AC_UL320_.jpg",
      "coupon": {
        "badge_text": "Save 15%",
        "text": "with coupon"
      },
      "is_prime": true,
      "rating": 3.3,
      "ratings_total": 447,
      "is_small_business": true,
      "prices": [
        {
          "symbol": "$",
          "value": 17.99,
          "currency": "USD",
          "raw": "$17.99",
          "name": "$17.99"
        },
        {
          "symbol": "$",
          "value": 17.09,
          "currency": "USD",
          "raw": "$17.09",
          "name": "$17.09"
        }
      ],
      "price": {
        "symbol": "$",
        "value": 17.99,
        "currency": "USD",
        "raw": "$17.99",
        "name": "$17.99"
      }
    },
    {
      "position": 40,
      "title": "Partake Brewing Non Alcoholic Craft Brew, Pale Ale, 12 Pack - 12 Ounce Cans, Low Calorie, All Natural Ingredients",
      "asin": "B099MR91RW",
      "link": "https://www.amazon.com/Partake-Brewing-Alcoholic-Craft-brew/dp/B099MR91RW/ref=sr_1_40?keywords=beer+alcoholic+drinks&qid=1667472794&qu=eyJxc2MiOiIyLjYxIiwicXNhIjoiMC4wMCIsInFzcCI6IjAuMDAifQ%3D%3D&sr=8-40",
      "categories": [
        {
          "name": "All Departments",
          "id": "aps"
        }
      ],
      "image": "https://m.media-amazon.com/images/I/61Xp-WMuaLL._AC_UL320_.jpg",
      "rating": 4.4,
      "ratings_total": 98,
      "prices": [
        {
          "symbol": "$",
          "value": 29.99,
          "currency": "USD",
          "raw": "$29.99",
          "name": "$29.99",
          "asin": "B099MR91RW",
          "link": "https://www.amazon.com/Partake-Brewing-Alcoholic-Craft-brew/dp/B099MR91RW/ref=sr_1_40?keywords=beer+alcoholic+drinks&qid=1667472794&qu=eyJxc2MiOiIyLjYxIiwicXNhIjoiMC4wMCIsInFzcCI6IjAuMDAifQ%3D%3D&sr=8-40"
        }
      ],
      "price": {
        "symbol": "$",
        "value": 29.99,
        "currency": "USD",
        "raw": "$29.99",
        "name": "$29.99",
        "asin": "B099MR91RW",
        "link": "https://www.amazon.com/Partake-Brewing-Alcoholic-Craft-brew/dp/B099MR91RW/ref=sr_1_40?keywords=beer+alcoholic+drinks&qid=1667472794&qu=eyJxc2MiOiIyLjYxIiwicXNhIjoiMC4wMCIsInFzcCI6IjAuMDAifQ%3D%3D&sr=8-40"
      }
    },
    {
      "position": 41,
      "title": "Lyre's American Malt Non-Alcoholic Spirit - Bourbon Style | Award Winning | 23.7 Fl Oz",
      "asin": "B08642C3QT",
      "link": "https://www.amazon.com/Lyres-American-Malt-Non-Alcoholic-Spirit/dp/B08642C3QT/ref=sr_1_41_mod_primary_new?keywords=beer+alcoholic+drinks&qid=1667472794&qu=eyJxc2MiOiIyLjYxIiwicXNhIjoiMC4wMCIsInFzcCI6IjAuMDAifQ%3D%3D&sbo=RZvfv%2F%2FHxDF%2BO5021pAnSA%3D%3D&sr=8-41",
      "categories": [
        {
          "name": "All Departments",
          "id": "aps"
        }
      ],
      "image": "https://m.media-amazon.com/images/I/81cBB2ZvC9L._AC_UL320_.jpg",
      "is_prime": true,
      "rating": 3.1,
      "ratings_total": 1240,
      "is_small_business": true,
      "prices": [
        {
          "symbol": "$",
          "value": 35.99,
          "currency": "USD",
          "raw": "$35.99",
          "name": "$35.99"
        },
        {
          "symbol": "$",
          "value": 32.39,
          "currency": "USD",
          "raw": "$32.39",
          "name": "$32.39"
        }
      ],
      "price": {
        "symbol": "$",
        "value": 35.99,
        "currency": "USD",
        "raw": "$35.99",
        "name": "$35.99"
      }
    },
    {
      "position": 42,
      "title": "Flying Cauldron Non-Alcoholic Butterscotch Beer 16.9 Fl Oz. 3 Pack",
      "asin": "B09RQD83B6",
      "link": "https://www.amazon.com/Flying-Cauldron-Non-Alcoholic-Butterscotch-Beer/dp/B09RQD83B6/ref=sr_1_42?keywords=beer+alcoholic+drinks&qid=1667472794&qu=eyJxc2MiOiIyLjYxIiwicXNhIjoiMC4wMCIsInFzcCI6IjAuMDAifQ%3D%3D&sr=8-42",
      "availability": {
        "raw": "Only 7 left in stock - order soon."
      },
      "categories": [
        {
          "name": "All Departments",
          "id": "aps"
        }
      ],
      "image": "https://m.media-amazon.com/images/I/61hx96Tru9L._AC_UL320_.jpg",
      "rating": 3.9,
      "ratings_total": 5,
      "prices": [
        {
          "symbol": "$",
          "value": 35.98,
          "currency": "USD",
          "raw": "$35.98",
          "name": "$35.98",
          "asin": "B09RQD83B6",
          "link": "https://www.amazon.com/Flying-Cauldron-Non-Alcoholic-Butterscotch-Beer/dp/B09RQD83B6/ref=sr_1_42?keywords=beer+alcoholic+drinks&qid=1667472794&qu=eyJxc2MiOiIyLjYxIiwicXNhIjoiMC4wMCIsInFzcCI6IjAuMDAifQ%3D%3D&sr=8-42"
        }
      ],
      "price": {
        "symbol": "$",
        "value": 35.98,
        "currency": "USD",
        "raw": "$35.98",
        "name": "$35.98",
        "asin": "B09RQD83B6",
        "link": "https://www.amazon.com/Flying-Cauldron-Non-Alcoholic-Butterscotch-Beer/dp/B09RQD83B6/ref=sr_1_42?keywords=beer+alcoholic+drinks&qid=1667472794&qu=eyJxc2MiOiIyLjYxIiwicXNhIjoiMC4wMCIsInFzcCI6IjAuMDAifQ%3D%3D&sr=8-42"
      }
    },
    {
      "position": 43,
      "title": "【PACK OF 6】 Heineken 0.0% Non Alcohol Beer - Great Taste, Zero Alcohol - 11.2 Fl Oz",
      "asin": "B07RLY2BKD",
      "link": "https://www.amazon.com/Heineken-0-0-Non-Alcohol-Beer/dp/B07RLY2BKD/ref=sr_1_43_mod_primary_new?keywords=beer+alcoholic+drinks&qid=1667472794&qu=eyJxc2MiOiIyLjYxIiwicXNhIjoiMC4wMCIsInFzcCI6IjAuMDAifQ%3D%3D&sbo=RZvfv%2F%2FHxDF%2BO5021pAnSA%3D%3D&sr=8-43",
      "categories": [
        {
          "name": "All Departments",
          "id": "aps"
        }
      ],
      "image": "https://m.media-amazon.com/images/I/71CwpPCLIeL._AC_UL320_.jpg",
      "is_prime": true,
      "rating": 4.1,
      "ratings_total": 168,
      "prices": [
        {
          "symbol": "$",
          "value": 22.98,
          "currency": "USD",
          "raw": "$22.98",
          "name": "$22.98"
        },
        {
          "symbol": "$",
          "value": 22.98,
          "currency": "USD",
          "raw": "$22.98",
          "name": "$22.98"
        }
      ],
      "price": {
        "symbol": "$",
        "value": 22.98,
        "currency": "USD",
        "raw": "$22.98",
        "name": "$22.98"
      }
    },
    {
      "position": 44,
      "title": "Kin Spritz by Kin Euphorics, Non Alcoholic Spirits, Ready to Drink, Adaptogen, Nootropic, Botanical, Fresh Citrus, Hibiscus, Caffeine, Rhodiola Rosea, Awaken the Mind, Uplift the Mood, 8 Fl Oz (4pk)",
      "asin": "B08DQ4QMFW",
      "link": "https://www.amazon.com/Euphorics-Botanic-Adaptogenic-Nootropic-Supplement/dp/B08DQ4QMFW/ref=sr_1_44?keywords=beer+alcoholic+drinks&qid=1667472794&qu=eyJxc2MiOiIyLjYxIiwicXNhIjoiMC4wMCIsInFzcCI6IjAuMDAifQ%3D%3D&sr=8-44",
      "categories": [
        {
          "name": "All Departments",
          "id": "aps"
        }
      ],
      "image": "https://m.media-amazon.com/images/I/71OUTqqd59L._AC_UL320_.jpg",
      "is_prime": true,
      "rating": 3.5,
      "ratings_total": 645,
      "is_small_business": true,
      "prices": [
        {
          "symbol": "$",
          "value": 22.53,
          "currency": "USD",
          "raw": "$22.53",
          "name": "$22.53",
          "asin": "B08DQ4QMFW",
          "link": "https://www.amazon.com/Euphorics-Botanic-Adaptogenic-Nootropic-Supplement/dp/B08DQ4QMFW/ref=sr_1_44?keywords=beer+alcoholic+drinks&qid=1667472794&qu=eyJxc2MiOiIyLjYxIiwicXNhIjoiMC4wMCIsInFzcCI6IjAuMDAifQ%3D%3D&sr=8-44"
        }
      ],
      "price": {
        "symbol": "$",
        "value": 22.53,
        "currency": "USD",
        "raw": "$22.53",
        "name": "$22.53",
        "asin": "B08DQ4QMFW",
        "link": "https://www.amazon.com/Euphorics-Botanic-Adaptogenic-Nootropic-Supplement/dp/B08DQ4QMFW/ref=sr_1_44?keywords=beer+alcoholic+drinks&qid=1667472794&qu=eyJxc2MiOiIyLjYxIiwicXNhIjoiMC4wMCIsInFzcCI6IjAuMDAifQ%3D%3D&sr=8-44"
      }
    },
    {
      "position": 45,
      "title": "Athletic Brewing Company Craft Non-Alcoholic Beer - 24 Pack x 12 Fl Oz Cans - Free Wave Hazy IPA - Low-Calorie, Award Winning - Loaded with Amarillo, Citra, and Mosaic Hops",
      "asin": "B091Q6LF23",
      "link": "https://www.amazon.com/Athletic-Brewing-Company-Craft-Low-Calorie/dp/B091Q6LF23/ref=sr_1_45?keywords=beer+alcoholic+drinks&qid=1667472794&qu=eyJxc2MiOiIyLjYxIiwicXNhIjoiMC4wMCIsInFzcCI6IjAuMDAifQ%3D%3D&sr=8-45",
      "categories": [
        {
          "name": "All Departments",
          "id": "aps"
        }
      ],
      "image": "https://m.media-amazon.com/images/I/61f2NDWzUrL._AC_UL320_.jpg",
      "rating": 4.8,
      "ratings_total": 15
    },
    {
      "position": 46,
      "title": "Athletic Brewing Company Craft Non-Alcoholic Beer - 24 Pack x 12 Fl Oz Cans - Upside Dawn Craft Golden - Low-Calorie, Award Winning - Subtle Aromas with Floral and Earthy Notes",
      "asin": "B08J4FWFZV",
      "link": "https://www.amazon.com/Athletic-Brewing-Company-Craft-Low-Calorie/dp/B08J4FWFZV/ref=sr_1_46?keywords=beer+alcoholic+drinks&qid=1667472794&qu=eyJxc2MiOiIyLjYxIiwicXNhIjoiMC4wMCIsInFzcCI6IjAuMDAifQ%3D%3D&sr=8-46",
      "categories": [
        {
          "name": "All Departments",
          "id": "aps"
        }
      ],
      "image": "https://m.media-amazon.com/images/I/610k1dywoHL._AC_UL320_.jpg",
      "rating": 4.7,
      "ratings_total": 39
    },
    {
      "position": 47,
      "title": "Wowie | Infused Sparkling Beverage for Stress and Anxiety Relief | All-Natural, Low Calorie | Non-alcoholic | Herbal Adaptogens Drink | 12oz Sleek Can",
      "asin": "B086FP44F4",
      "link": "https://www.amazon.com/Tranquini-Hemp-Infused-Adaptogens-All-Natural-Relaxation/dp/B086FP44F4/ref=sr_1_47_mod_primary_new?keywords=beer+alcoholic+drinks&qid=1667472794&qu=eyJxc2MiOiIyLjYxIiwicXNhIjoiMC4wMCIsInFzcCI6IjAuMDAifQ%3D%3D&sbo=RZvfv%2F%2FHxDF%2BO5021pAnSA%3D%3D&sr=8-47",
      "categories": [
        {
          "name": "All Departments",
          "id": "aps"
        }
      ],
      "image": "https://m.media-amazon.com/images/I/61UEZwtQ-zL._AC_UL320_.jpg",
      "is_prime": true,
      "rating": 3.7,
      "ratings_total": 252,
      "is_small_business": true,
      "prices": [
        {
          "symbol": "$",
          "value": 21.95,
          "currency": "USD",
          "raw": "$21.95",
          "name": "$21.95"
        },
        {
          "symbol": "$",
          "value": 21.95,
          "currency": "USD",
          "raw": "$21.95",
          "name": "$21.95"
        }
      ],
      "price": {
        "symbol": "$",
        "value": 21.95,
        "currency": "USD",
        "raw": "$21.95",
        "name": "$21.95"
      }
    },
    {
      "position": 48,
      "title": "Seedlip Grove 42 - Non-alcoholic Spirit | Calorie Free, Sugar Free | Spirits Alternative | Alcohol Free Cocktails | 23.7fl oz (700ml)…",
      "asin": "B07HXR49YM",
      "link": "https://www.amazon.com/Seedlip-Grove-Non-alcoholic-alcoholic-Cocktails/dp/B07HXR49YM/ref=sr_1_48_mod_primary_new?keywords=beer+alcoholic+drinks&qid=1667472794&qu=eyJxc2MiOiIyLjYxIiwicXNhIjoiMC4wMCIsInFzcCI6IjAuMDAifQ%3D%3D&sbo=RZvfv%2F%2FHxDF%2BO5021pAnSA%3D%3D&sr=8-48",
      "categories": [
        {
          "name": "All Departments",
          "id": "aps"
        }
      ],
      "image": "https://m.media-amazon.com/images/I/71kOWU2F5pL._AC_UL320_.jpg",
      "coupon": {
        "badge_text": "Save 25%",
        "text": "with coupon"
      },
      "is_prime": true,
      "rating": 3.6,
      "ratings_total": 1890,
      "prices": [
        {
          "symbol": "$",
          "value": 31.99,
          "currency": "USD",
          "raw": "$31.99",
          "name": "$31.99"
        },
        {
          "symbol": "$",
          "value": 28.79,
          "currency": "USD",
          "raw": "$28.79",
          "name": "$28.79"
        }
      ],
      "price": {
        "symbol": "$",
        "value": 31.99,
        "currency": "USD",
        "raw": "$31.99",
        "name": "$31.99"
      }
    }
  ]
}